podcast_log/__init__.py
podcast_log/__version__.py
podcast_log/admin.py
podcast_log/apps.py
podcast_log/forms.py
podcast_log/models.py
podcast_log/tables.py
podcast_log/tasks.py
podcast_log/tests.py
podcast_log/urls.py
podcast_log/views.py
podcast_log/migrations/0001_initial.py
podcast_log/migrations/0002_podcast_url.py
podcast_log/migrations/0003_auto_20190115_1516.py
podcast_log/migrations/0004_episode_podcast.py
podcast_log/migrations/0005_auto_20190116_0444.py
podcast_log/migrations/0006_auto_20190116_0448.py
podcast_log/migrations/0007_auto_20190116_1916.py
podcast_log/migrations/0008_auto_20190116_1917.py
podcast_log/migrations/0009_auto_20190116_1922.py
podcast_log/migrations/0010_episode_status.py
podcast_log/migrations/__init__.py
podcast_log-0.2.1.dist-info/METADATA
podcast_log-0.2.1.dist-info/WHEEL
podcast_log-0.2.1.dist-info/top_level.txt
podcast_log-0.2.1.dist-info/RECORD
